omagent_core/__init__.py
omagent_core/advanced_components/__init__.py
omagent_core/advanced_components/worker/__init__.py
omagent_core/advanced_components/worker/conclude/__init__.py
omagent_core/advanced_components/worker/conqueror/__init__.py
omagent_core/advanced_components/worker/divider/__init__.py
omagent_core/advanced_components/worker/task_exit_monitor/__init__.py
omagent_core/advanced_components/worker/video_preprocess/__init__.py
omagent_core/advanced_components/workflow/ToT/README.md
omagent_core/advanced_components/workflow/ToT/__init__.py
omagent_core/advanced_components/workflow/ToT/agent/search_algorithm/search_algorithm.py
omagent_core/advanced_components/workflow/ToT/agent/search_algorithm/sys_prompt.prompt
omagent_core/advanced_components/workflow/ToT/agent/search_algorithm/user_prompt.prompt
omagent_core/advanced_components/workflow/ToT/agent/state_evaluator/__init__.py
omagent_core/advanced_components/workflow/ToT/agent/state_evaluator/state_evaluator.py
omagent_core/advanced_components/workflow/ToT/agent/state_evaluator/value_sys.prompt
omagent_core/advanced_components/workflow/ToT/agent/state_evaluator/value_user.prompt
omagent_core/advanced_components/workflow/ToT/agent/state_evaluator/vote_sys.prompt
omagent_core/advanced_components/workflow/ToT/agent/state_evaluator/vote_user.prompt
omagent_core/advanced_components/workflow/ToT/agent/thought_decomposition/__init__.py
omagent_core/advanced_components/workflow/ToT/agent/thought_decomposition/thought_decomposition.py
omagent_core/advanced_components/workflow/ToT/agent/thought_generator/__init__.py
omagent_core/advanced_components/workflow/ToT/agent/thought_generator/sys_prompt.prompt
omagent_core/advanced_components/workflow/ToT/agent/thought_generator/thought_generator.py
omagent_core/advanced_components/workflow/ToT/agent/thought_generator/user_prompt.prompt
omagent_core/advanced_components/workflow/ToT/schemas/ToT_structure.py
omagent_core/advanced_components/workflow/ToT/workflow.py
omagent_core-0.2.4.dist-info/LICENSE
omagent_core-0.2.4.dist-info/METADATA
omagent_core-0.2.4.dist-info/WHEEL
omagent_core-0.2.4.dist-info/RECORD
